nccommons/__init__.py
nccommons/decode.py
nccommons/emails.py
nccommons/jsons.py
nccommons-0.1.6.dist-info/LICENSE
nccommons-0.1.6.dist-info/METADATA
nccommons-0.1.6.dist-info/WHEEL
nccommons-0.1.6.dist-info/top_level.txt
nccommons-0.1.6.dist-info/RECORD
