Metadata-Version: 2.1
Name: nccommons
Version: 0.1.6
Summary: This package provides common functions that can be used in API or UI Automation
Home-page: https://github.com/abhishek.maurya/Abhishekkapackage
Author: Abhishek Maurya
Author-email: testmartech1@netcorecloud.com
License: UNKNOWN
Platform: UNKNOWN
Classifier: Programming Language :: Python :: 3
Classifier: License :: OSI Approved :: MIT License
Classifier: Operating System :: OS Independent
Requires-Python: >=3.6
License-File: LICENSE
